LICENSE
neatlogger/__init__.py
neatlogger/neatlogger.py
neatlogger-0.1.2.dist-info/LICENSE
neatlogger-0.1.2.dist-info/METADATA
neatlogger-0.1.2.dist-info/WHEEL
neatlogger-0.1.2.dist-info/RECORD
