Metadata-Version: 2.1
Name: Neatlogger
Version: 0.1.2
Summary: Neat adaptions to the loguru package which wraps logging in python.
Home-page: https://github.com/mschroen/neatlogger
License: MIT
Keywords: logging
Author: Martin Schrön
Author-email: martin@schroen.eu
Requires-Python: >3.9
Classifier: License :: OSI Approved :: MIT License
Classifier: Programming Language :: Python :: 3
Classifier: Programming Language :: Python :: 3.10
Classifier: Programming Language :: Python :: 3.11
Classifier: Programming Language :: Python :: 3.12
Classifier: Programming Language :: Python :: 3.13
Requires-Dist: loguru (>0.7)
Project-URL: Repository, https://github.com/mschroen/neatlogger
